Metadata-Version: 2.1
Name: PyMailGw
Version: 0.0.1
Summary: Mail.gw rest api wrapper.
Home-page: https://github.com/Its-Vichy/PyMailGw
Author: Its_Vichy
Author-email: its_vichy@protonmail.com
License: MIT License
Keywords: temp mail tempmail mail.gw
Platform: UNKNOWN
Classifier: Programming Language :: Python
Classifier: Programming Language :: Python :: 2
Classifier: Programming Language :: Python :: 2.7
Classifier: Programming Language :: Python :: 3
Classifier: Programming Language :: Python :: 3.5
Classifier: Programming Language :: Python :: 3.6
Classifier: Programming Language :: Python :: 3.7
Classifier: Programming Language :: Python :: 3.8
Classifier: Programming Language :: Python :: 3.9
Classifier: Programming Language :: Python :: 3.10
